smart_importer/__init__.py
smart_importer/entries.py
smart_importer/pipelines.py
smart_importer/predictor.py
smart_importer/py.typed
smart_importer/wrapper.py
smart_importer-1.2.dist-info/licenses/LICENSE
smart_importer-1.2.dist-info/METADATA
smart_importer-1.2.dist-info/WHEEL
smart_importer-1.2.dist-info/top_level.txt
smart_importer-1.2.dist-info/RECORD
