Metadata-Version: 2.4
Name: smart_importer
Version: 1.2
Summary: Augment Beancount importers with machine learning functionality.
Home-page: https://github.com/beancount/smart_importer
Author: Johannes Harms
License: MIT
Keywords: fava beancount accounting machinelearning
Classifier: Development Status :: 1 - Planning
Classifier: Environment :: Web Environment
Classifier: Environment :: Console
Classifier: Intended Audience :: Education
Classifier: Intended Audience :: End Users/Desktop
Classifier: Intended Audience :: Financial and Insurance Industry
Classifier: Intended Audience :: Information Technology
Classifier: Natural Language :: English
Classifier: Programming Language :: Python :: 3 :: Only
Classifier: Programming Language :: Python :: 3.9
Classifier: Programming Language :: Python :: 3.10
Classifier: Programming Language :: Python :: 3.11
Classifier: Programming Language :: Python :: 3.12
Classifier: Programming Language :: Python :: 3.13
Classifier: Topic :: Office/Business :: Financial :: Accounting
Classifier: Topic :: Office/Business :: Financial :: Investment
License-File: LICENSE
Requires-Dist: beancount>=3
Requires-Dist: beangulp
Requires-Dist: scikit-learn>=1.0
Requires-Dist: numpy>=1.18.0
Requires-Dist: typing-extensions>=4.9
Dynamic: license-file
